LICENSE
README.md
setup.py
kktools/FX.py
kktools/ISO20022.py
kktools/__init__.py
kktools/core.py
kktools.egg-info/PKG-INFO
kktools.egg-info/SOURCES.txt
kktools.egg-info/dependency_links.txt
kktools.egg-info/requires.txt
kktools.egg-info/top_level.txt