Metadata-Version: 2.1
Name: kktools
Version: 4.28
Summary: Tools for finance and treasury specialists
Home-page: https://github.com/khorevkp/KK_Tools
Author: Konstantin Khorev
Author-email: khorevkp@gmail.com
License: UNKNOWN
Platform: UNKNOWN
License-File: LICENSE
